setup.py
DroneDataConversion/DroneDataConversion.py
DroneDataConversion/__init__.py
DroneDataConversion.egg-info/PKG-INFO
DroneDataConversion.egg-info/SOURCES.txt
DroneDataConversion.egg-info/dependency_links.txt
DroneDataConversion.egg-info/requires.txt
DroneDataConversion.egg-info/top_level.txt