Metadata-Version: 1.0
Name: DroneDataConversion
Version: 0.5
Summary: Parses Bebop Drones flight logs for further processing and analysis
Home-page: https://johanneskinzig.de/software-development/python-parser-bebop-logs.html
Author: Johannes Kinzig
Author-email: johannes_kinzig@icloud.com
License: Apache License, Version 2.0
Keywords: extract parrot bebop convert gpx pud json
Platform: UNKNOWN
